Qdraco/__init__.py
Qdraco/attack_patterns.py
Qdraco/validator.py
Qdraco-1.1.dist-info/LICENSE
Qdraco-1.1.dist-info/METADATA
Qdraco-1.1.dist-info/WHEEL
Qdraco-1.1.dist-info/top_level.txt
Qdraco-1.1.dist-info/RECORD
