Metadata-Version: 2.1
Name: Qdraco
Version: 1.1
Summary: A library for validating user inputs to prevent common security vulnerabilities.
Home-page: https://github.com/qaisdraco/QDraco
Author: Qais Abou Shaheen
License: UNKNOWN
Platform: UNKNOWN
Classifier: Programming Language :: Python :: 3
Classifier: License :: OSI Approved :: MIT License
Classifier: Operating System :: OS Independent
Requires-Python: >=3.6
